github_team_organizer/classes/base.py
github_team_organizer/classes/ghgql.py
github_team_organizer/classes/github.py
github_team_organizer/classes/organization.py
github_team_organizer/classes/project.py
github_team_organizer/classes/repository.py
github_team_organizer/classes/settings.py
github_team_organizer/classes/team.py
github_team_organizer/graphql/github_schema.py
github_team_organizer/scripts/organizer.py
github_team_organizer-0.4.2.17.dist-info/LICENSE
github_team_organizer-0.4.2.17.dist-info/METADATA
github_team_organizer-0.4.2.17.dist-info/WHEEL
github_team_organizer-0.4.2.17.dist-info/entry_points.txt
github_team_organizer-0.4.2.17.dist-info/top_level.txt
github_team_organizer-0.4.2.17.dist-info/RECORD
