Metadata-Version: 2.1
Name: github-team-organizer
Version: 0.4.2.17
Summary: Tool for organizing your GitHub Organization
Home-page: https://soar.name
Author: soar
Author-email: i@soar.name
License: MIT
Platform: UNKNOWN
Classifier: Intended Audience :: Developers
Classifier: License :: OSI Approved :: MIT License
Classifier: Operating System :: OS Independent
Classifier: Programming Language :: Python
Classifier: Programming Language :: Python :: 3 :: Only
Requires-Dist: cached-property (<1.6,>=1.5)
Requires-Dist: click (<7.2,>=7.1)
Requires-Dist: sgqlc (<11,>=10.1)
Requires-Dist: pygithub (<1.48,>=1.47)
Requires-Dist: python-dotenv (<0.13,>=0.12)
